{"nombre":"Lorena","email":"Lorena@silvana.com","password":"$2y$10$8.2OPa3\/sWbaLaRSr.eXmeTbMYd4\/1w5sb4Ia3aYPtl2pIKW4nOru"}
{"nombre":"sabrina","email":"sabrina@jaime.com","password":"$2y$10$Umi2bF2A3D08Hi7EZ2WuI.kQw8kepIQ12okzQ5vlOsFJRTrvvvaaG"}
{"nombre":"Mijael Volker","email":"mijael_volker@hotmail.com","password":"$2y$10$4YSV5rF6qm7r\/hfmKI6hP.KHGJDfZHzb0Afv3egQmkYwK3AX9av2q"}
{"nombre":"Mijael Volker","email":"mijael_volker@hotmail.com","password":"$2y$10$pw46jj2iQFeHIP7XIaGxXeIFfZIf98OYawT5SEgcGs.o\/eA7qMcH2"}
{"nombre":"seba","email":"seba@gmail.com","password":"$2y$10$CKTFbhJzRHXjAp2d6SigFeyJ1Y9I9zaAqPpqNnpLp4xFQKz8GFTY6"}
